guildreader/__init__.py
guildreader/jsonreader.py
guildreader-2.0.2.dist-info/LICENSE
guildreader-2.0.2.dist-info/METADATA
guildreader-2.0.2.dist-info/WHEEL
guildreader-2.0.2.dist-info/top_level.txt
guildreader-2.0.2.dist-info/RECORD
