Metadata-Version: 2.1
Name: guildreader
Version: 2.0.2
Summary: JSON Data Management Module
Home-page: https://github.com/redmoogle/jsonreader
Author: Redmoogle
Author-email: dakotamew@gmail.com
License: UNKNOWN
Platform: UNKNOWN
Classifier: Development Status :: 5 - Production/Stable
Classifier: Intended Audience :: Developers
Classifier: Natural Language :: English
Classifier: Programming Language :: Python :: 3
Classifier: License :: OSI Approved :: MIT License
Classifier: Operating System :: OS Independent
Requires-Python: >=3.5
Requires-Dist: ujson
